README.rst
kvstore.py
setup.py
kvstore.egg-info/PKG-INFO
kvstore.egg-info/SOURCES.txt
kvstore.egg-info/dependency_links.txt
kvstore.egg-info/requires.txt
kvstore.egg-info/top_level.txt