Metadata-Version: 1.1
Name: kvstore
Version: 0.1.1
Summary: Generic Python K/V Store Client
Home-page: https://github.com/javicacheiro/kvstore
Author: Javier Cacheiro
Author-email: javier.cacheiro@gmail.com
License: MIT
Platform: UNKNOWN
Classifier: License :: OSI Approved :: MIT License
Classifier: Intended Audience :: Developers
Classifier: Intended Audience :: System Administrators
Classifier: Operating System :: OS Independent
Classifier: Topic :: Software Development :: Libraries :: Python Modules
